{
    "name": "root",
    "gauges": {
        "match_0_SoccerTwos.Policy.Entropy.mean": {
            "value": 3.181523561477661,
            "min": 3.181523561477661,
            "max": 3.2957613468170166,
            "count": 56
        },
        "match_0_SoccerTwos.Environment.EpisodeLength.mean": {
            "value": 507.75,
            "min": 458.27272727272725,
            "max": 599.0,
            "count": 56
        },
        "match_0_SoccerTwos.Self-play.ELO.mean": {
            "value": 1206.1823522915267,
            "min": 1200.9494558522063,
            "max": 1206.561084213678,
            "count": 56
        },
        "match_0_SoccerTwos.Policy.ExtrinsicValueEstimate.mean": {
            "value": 0.006541042122989893,
            "min": 0.00197393586859107,
            "max": 0.08858737349510193,
            "count": 56
        },
        "match_0_SoccerTwos.Environment.CumulativeReward.mean": {
            "value": -0.019950073957443238,
            "min": -0.125,
            "max": 0.10312237237629138,
            "count": 56
        },
        "match_0_SoccerTwos.Policy.ExtrinsicReward.mean": {
            "value": -0.019950073957443238,
            "min": -0.125,
            "max": 0.10312237237629138,
            "count": 56
        },
        "match_0_SoccerTwos.IsTraining.mean": {
            "value": 1.0,
            "min": 1.0,
            "max": 1.0,
            "count": 56
        },
        "match_0_SoccerTwos.Losses.ValueLoss.mean": {
            "value": 0.0037645376287400723,
            "min": 0.0003705980780068785,
            "max": 0.016058579087257385,
            "count": 25
        },
        "match_0_SoccerTwos.Losses.PolicyLoss.mean": {
            "value": 0.018209170550107956,
            "min": 0.011377857998013496,
            "max": 0.02225886657834053,
            "count": 25
        },
        "match_0_SoccerTwos.Policy.LearningRate.mean": {
            "value": 0.00030000004335306585,
            "min": 0.0003000000142492354,
            "max": 0.00030000010156072676,
            "count": 25
        }
    },
    "metadata": {
        "timer_format_version": "0.1.0",
        "start_time_seconds": "1590975084",
        "python_version": "3.7.3 (default, Apr 24 2020, 18:51:23) \n[Clang 11.0.3 (clang-1103.0.32.62)]",
        "command_line_arguments": "/Users/rsaenz/Library/Python/3.7/bin/mlagents-learn config/trainer_config.yaml --env SoccerAcademy --force --run-id match_0 --save-freq 10000 --num-envs 1",
        "mlagents_version": "0.16.1",
        "mlagents_envs_version": "0.16.1",
        "communication_protocol_version": "1.0.0",
        "tensorflow_version": "2.2.0",
        "end_time_seconds": "1590975954"
    },
    "total": 870.5526233960001,
    "count": 1,
    "self": 0.0006539060001387043,
    "children": {
        "run_training.setup": {
            "total": 0.01097445900000027,
            "count": 1,
            "self": 0.01097445900000027
        },
        "TrainerController.start_learning": {
            "total": 870.540995031,
            "count": 1,
            "self": 39.54711785999666,
            "children": {
                "TrainerController._reset_env": {
                    "total": 3.0531494479999965,
                    "count": 3,
                    "self": 3.0531494479999965
                },
                "TrainerController.advance": {
                    "total": 826.0916451270033,
                    "count": 29477,
                    "self": 0.4955552470017892,
                    "children": {
                        "env_step": {
                            "total": 825.5960898800015,
                            "count": 29477,
                            "self": 694.8791243350158,
                            "children": {
                                "SubprocessEnvManager._take_step": {
                                    "total": 130.2015211939966,
                                    "count": 29477,
                                    "self": 3.967694289992181,
                                    "children": {
                                        "NNPolicy.evaluate": {
                                            "total": 126.23382690400442,
                                            "count": 57854,
                                            "self": 126.23382690400442
                                        }
                                    }
                                },
                                "workers": {
                                    "total": 0.5154443509890339,
                                    "count": 29476,
                                    "self": 0.0,
                                    "children": {
                                        "worker_root": {
                                            "total": 867.5232366840054,
                                            "count": 29476,
                                            "is_parallel": true,
                                            "self": 312.60701750699025,
                                            "children": {
                                                "run_training.setup": {
                                                    "total": 0.0,
                                                    "count": 0,
                                                    "is_parallel": true,
                                                    "self": 0.0,
                                                    "children": {
                                                        "steps_from_proto": {
                                                            "total": 0.005179101999999602,
                                                            "count": 2,
                                                            "is_parallel": true,
                                                            "self": 0.0009103789999977963,
                                                            "children": {
                                                                "_process_vector_observation": {
                                                                    "total": 0.004268723000001806,
                                                                    "count": 8,
                                                                    "is_parallel": true,
                                                                    "self": 0.004268723000001806
                                                                }
                                                            }
                                                        },
                                                        "UnityEnvironment.step": {
                                                            "total": 0.05043171199999996,
                                                            "count": 1,
                                                            "is_parallel": true,
                                                            "self": 0.001302313000000055,
                                                            "children": {
                                                                "UnityEnvironment._generate_step_input": {
                                                                    "total": 0.0004338090000004513,
                                                                    "count": 1,
                                                                    "is_parallel": true,
                                                                    "self": 0.0004338090000004513
                                                                },
                                                                "communicator.exchange": {
                                                                    "total": 0.043580675999999485,
                                                                    "count": 1,
                                                                    "is_parallel": true,
                                                                    "self": 0.043580675999999485
                                                                },
                                                                "steps_from_proto": {
                                                                    "total": 0.00511491399999997,
                                                                    "count": 2,
                                                                    "is_parallel": true,
                                                                    "self": 0.0005768259999996417,
                                                                    "children": {
                                                                        "_process_vector_observation": {
                                                                            "total": 0.004538088000000329,
                                                                            "count": 8,
                                                                            "is_parallel": true,
                                                                            "self": 0.004538088000000329
                                                                        }
                                                                    }
                                                                }
                                                            }
                                                        }
                                                    }
                                                },
                                                "UnityEnvironment.step": {
                                                    "total": 554.906372056015,
                                                    "count": 29475,
                                                    "is_parallel": true,
                                                    "self": 29.654111790030356,
                                                    "children": {
                                                        "UnityEnvironment._generate_step_input": {
                                                            "total": 12.431728571991068,
                                                            "count": 29475,
                                                            "is_parallel": true,
                                                            "self": 12.431728571991068
                                                        },
                                                        "communicator.exchange": {
                                                            "total": 382.35804693000523,
                                                            "count": 29475,
                                                            "is_parallel": true,
                                                            "self": 382.35804693000523
                                                        },
                                                        "steps_from_proto": {
                                                            "total": 130.46248476398836,
                                                            "count": 58950,
                                                            "is_parallel": true,
                                                            "self": 15.843994685981187,
                                                            "children": {
                                                                "_process_vector_observation": {
                                                                    "total": 114.61849007800717,
                                                                    "count": 235800,
                                                                    "is_parallel": true,
                                                                    "self": 114.61849007800717
                                                                }
                                                            }
                                                        }
                                                    }
                                                },
                                                "steps_from_proto": {
                                                    "total": 0.009847121000063908,
                                                    "count": 4,
                                                    "is_parallel": true,
                                                    "self": 0.0012114490000953992,
                                                    "children": {
                                                        "_process_vector_observation": {
                                                            "total": 0.008635671999968508,
                                                            "count": 16,
                                                            "is_parallel": true,
                                                            "self": 0.008635671999968508
                                                        }
                                                    }
                                                }
                                            }
                                        }
                                    }
                                }
                            }
                        }
                    }
                },
                "TrainerController._save_model": {
                    "total": 1.8490459880000572,
                    "count": 3,
                    "self": 1.8490459880000572
                },
                "trainer_threads": {
                    "total": 3.660799995941488e-05,
                    "count": 1,
                    "self": 3.660799995941488e-05,
                    "children": {
                        "thread_root": {
                            "total": 0.0,
                            "count": 0,
                            "is_parallel": true,
                            "self": 0.0,
                            "children": {
                                "trainer_advance": {
                                    "total": 857.3162516200229,
                                    "count": 380129,
                                    "is_parallel": true,
                                    "self": 597.0572326800209,
                                    "children": {
                                        "process_trajectory": {
                                            "total": 133.29886032800204,
                                            "count": 380129,
                                            "is_parallel": true,
                                            "self": 133.29886032800204
                                        },
                                        "_update_policy": {
                                            "total": 126.96015861199987,
                                            "count": 25,
                                            "is_parallel": true,
                                            "self": 54.70838872499908,
                                            "children": {
                                                "PPOOptimizer.update": {
                                                    "total": 72.25176988700079,
                                                    "count": 783,
                                                    "is_parallel": true,
                                                    "self": 72.25176988700079
                                                }
                                            }
                                        }
                                    }
                                }
                            }
                        }
                    }
                }
            }
        }
    }
}